[1,["45go8ltQ1MUqWR4ZSRpiuM@f9941","319DAHeLNG/qea7QX42VzS@f9941","319DAHeLNG/qea7QX42VzS@6c48a"],["node","_spriteFrame","root","data","_textureSource"],[["cc.Node",["_name","_layer","_components","_prefab","_parent","_lpos","_children","_lscale"],1,9,4,1,5,2,5],["cc.UITransform",["node","__prefab","_contentSize"],3,1,4,5],["cc.Sprite",["_sizeMode","_isTrimmedMode","node","__prefab","_spriteFrame"],1,1,4,6],"cc.SpriteFrame",["cc.Prefab",["_name"],2],["cc.CompPrefabInfo",["fileId"],2],["cc.PrefabInfo",["fileId","instance","targetOverrides","nestedPrefabInstanceRoots","root","asset"],-1,1,1]],[[5,0,2],[6,0,1,2,3,4,5,5],[1,0,1,2,1],[0,0,1,4,2,3,5,3],[2,2,3,4,1],[1,0,1,1],[2,0,1,2,3,4,3],[4,0,2],[0,0,1,6,2,3,3],[0,0,1,4,6,2,3,5,3],[0,0,1,4,6,2,3,5,7,3],[0,0,1,4,2,3,5,7,3]],[[[[7,"scene_item_10038"],[8,"scene_item_10038",1,[-3,-4,-5,-6],[[2,-2,[0,"7dXdc/OfdEW6unZRSl7cqp"],[5,260,260]]],[1,"687blJ+qBHaJdgr+r1KTNu",null,null,null,-1,0]],[9,"points1",1,1,[-8,-9,-10,-11,-12,-13],[[5,-7,[0,"87LMrcA21LsJVL+ZqjJrY5"]]],[1,"04tT6+CnBOE7zyw56pnGHs",null,null,null,1,0],[1,11.366,-72.084,0]],[10,"points2",1,1,[-15,-16,-17,-18,-19,-20],[[5,-14,[0,"2eiJXG5rZNlYpSnwa1J1Ig"]]],[1,"58yLbp8+VBwa4A2b9aKg2f",null,null,null,1,0],[1,10.583,-71.018,0],[1,-1,1,1]],[3,"icon1",1,1,[[2,-21,[0,"cfzEeiLt9DK4gMTVpjj04s"],[5,395,415]],[6,2,false,-22,[0,"3bWnRDB5lKvYeo6i2YC/av"],0]],[1,"3cmCEwn35IKa3hkU9E8Npl",null,null,null,1,0],[1,11.772,66.851,0]],[11,"icon2",1,1,[[2,-23,[0,"98JlE46ehIJLvq7CzLE1U7"],[5,395,415]],[6,2,false,-24,[0,"d8CMyHlwxJ178cgLcxTe1C"],1]],[1,"08IAsUJdNO34CMA6CaNlpk",null,null,null,1,0],[1,3.348,67.771,0],[1,-1,1,1]],[3,"pos1",1,2,[[2,-25,[0,"dfWiKE92xD5rUHL0yJVxS7"],[5,30,30]],[4,-26,[0,"0bslviZYRER4t7pZhxbXSP"],2]],[1,"b91hCo895IjpfP4aXQ8GqP",null,null,null,1,0],[1,-22.3,187.776,0]],[3,"pos2",1,2,[[2,-27,[0,"51JCvfmalJ1pXwSPyqfEfn"],[5,30,30]],[4,-28,[0,"1eTezoVipNJbSnPwDNmYAl"],3]],[1,"b5IHanYbtNxrfIDaLczaJV",null,null,null,1,0],[1,-82.152,158.168,0]],[3,"pos3",1,2,[[2,-29,[0,"21v+AID6xEgKUx7YW2F46j"],[5,30,30]],[4,-30,[0,"4do2CLqPxNXKAEHxL8IPHX"],4]],[1,"0dAYO35ZlJOIMWyPvsP4qA",null,null,null,1,0],[1,-84.542,15.148,0]],[3,"pos4",1,2,[[2,-31,[0,"09WD4F5tRG76qtVhLg5GXx"],[5,30,30]],[4,-32,[0,"cfGjw5w7dOorAghZVdPjjy"],5]],[1,"c30kkUfrRAoo/oWTyjNsjK",null,null,null,1,0],[1,4.964,-20.592,0]],[3,"pos5",1,2,[[2,-33,[0,"60LWv1vUZIPpoOE3unt6/l"],[5,30,30]],[4,-34,[0,"d6tYo9f/ZPRIGbRH1AvYjp"],6]],[1,"6ciGyIy8VHH5MWkDYhtJNv",null,null,null,1,0],[1,79.135,16.953,0]],[3,"pos6",1,2,[[2,-35,[0,"b0duiePMdJl7q6192xB0+N"],[5,30,30]],[4,-36,[0,"d2aSbAzJFEKI3OUVUk4rle"],7]],[1,"912W0nFRFCM4NquKrpYkaO",null,null,null,1,0],[1,54.633,108.959,0]],[3,"pos1",1,3,[[2,-37,[0,"dfeo+gDepH4rx/FP2s9t5a"],[5,30,30]],[4,-38,[0,"a1kekztX1HlaOunZeT6xl2"],8]],[1,"c74J3JJKNNIa5ql/VmaJBO",null,null,null,1,0],[1,-22.3,187.776,0]],[3,"pos2",1,3,[[2,-39,[0,"a2t1AZXkFKZa8jE/iXktC8"],[5,30,30]],[4,-40,[0,"f646hxL3JGjaZ2D6xerZG/"],9]],[1,"23gVE+p25LtqIUjxSYstDW",null,null,null,1,0],[1,-82.152,158.168,0]],[3,"pos3",1,3,[[2,-41,[0,"9f9T91vFBNPK8EwXl/L8II"],[5,30,30]],[4,-42,[0,"58gZ07RG9HY5vy41d+K2eY"],10]],[1,"66Am3XfapJlYamJKOqyt6p",null,null,null,1,0],[1,-84.542,15.148,0]],[3,"pos4",1,3,[[2,-43,[0,"23Bxqs1thDGoeWsOxm0tZg"],[5,30,30]],[4,-44,[0,"d57HuhOSdJj6Z0ef7xexZK"],11]],[1,"00VyoTV/tG3rSop/KWxxBt",null,null,null,1,0],[1,4.964,-20.592,0]],[3,"pos5",1,3,[[2,-45,[0,"71SWJvRPFErbe0LRdKHOw/"],[5,30,30]],[4,-46,[0,"e5iNWPrn9E36TlOGM7ptnR"],12]],[1,"3c7XMI6ERIDa47sMLF/TXH",null,null,null,1,0],[1,79.135,16.953,0]],[3,"pos6",1,3,[[2,-47,[0,"95nJ8DOjVF55pBDTcqF3jt"],[5,30,30]],[4,-48,[0,"84BdFxLNdI/q2jKnwkMnE+"],13]],[1,"805zbLDchNZ6S8wgdhZCzb",null,null,null,1,0],[1,54.633,108.959,0]]],0,[0,2,1,0,0,1,0,-1,4,0,-2,5,0,-3,2,0,-4,3,0,0,2,0,-1,6,0,-2,7,0,-3,8,0,-4,9,0,-5,10,0,-6,11,0,0,3,0,-1,12,0,-2,13,0,-3,14,0,-4,15,0,-5,16,0,-6,17,0,0,4,0,0,4,0,0,5,0,0,5,0,0,6,0,0,6,0,0,7,0,0,7,0,0,8,0,0,8,0,0,9,0,0,9,0,0,10,0,0,10,0,0,11,0,0,11,0,0,12,0,0,12,0,0,13,0,0,13,0,0,14,0,0,14,0,0,15,0,0,15,0,0,16,0,0,16,0,0,17,0,0,17,0,3,1,48],[0,0,0,0,0,0,0,0,0,0,0,0,0,0],[1,1,1,1,1,1,1,1,1,1,1,1,1,1],[1,1,0,0,0,0,0,0,0,0,0,0,0,0]],[[{"name":"scene_item_1003801","rect":{"x":110,"y":150,"width":169,"height":221},"offset":{"x":-3,"y":-53},"originalSize":{"width":395,"height":415},"rotated":false,"capInsets":[0,0,0,0],"vertices":{"rawPosition":[-84.5,-110.5,0,84.5,-110.5,0,-84.5,110.5,0,84.5,110.5,0],"indexes":[0,1,2,2,1,3],"uv":[110,265,279,265,110,44,279,44],"nuv":[0.27848101265822783,0.10602409638554217,0.7063291139240506,0.10602409638554217,0.27848101265822783,0.6385542168674698,0.7063291139240506,0.6385542168674698],"minPos":{"x":-84.5,"y":-110.5,"z":0},"maxPos":{"x":84.5,"y":110.5,"z":0}},"packable":true,"pixelsToUnit":100,"pivot":{"x":0.5,"y":0.5},"meshType":0}],[3],0,[0],[4],[2]]]]
