[1,["45go8ltQ1MUqWR4ZSRpiuM@f9941","d5Qj9vf95FzbkSmm1mijoM@f9941","d5Qj9vf95FzbkSmm1mijoM@6c48a"],["node","_spriteFrame","root","data","_textureSource"],[["cc.Node",["_name","_layer","_components","_prefab","_parent","_lpos","_children","_lscale"],1,9,4,1,5,2,5],["cc.UITransform",["node","__prefab","_contentSize"],3,1,4,5],["cc.Sprite",["_sizeMode","_isTrimmedMode","node","__prefab","_spriteFrame"],1,1,4,6],"cc.SpriteFrame",["cc.Prefab",["_name"],2],["cc.CompPrefabInfo",["fileId"],2],["cc.PrefabInfo",["fileId","instance","targetOverrides","nestedPrefabInstanceRoots","root","asset"],-1,1,1]],[[5,0,2],[6,0,1,2,3,4,5,5],[1,0,1,2,1],[0,0,1,4,2,3,5,3],[2,2,3,4,1],[1,0,1,1],[2,0,1,2,3,4,3],[4,0,2],[0,0,1,6,2,3,3],[0,0,1,4,6,2,3,5,3],[0,0,1,4,6,2,3,5,7,3],[0,0,1,4,2,3,5,7,3]],[[[[7,"scene_item_10015"],[8,"scene_item_10015",1,[-3,-4,-5,-6],[[2,-2,[0,"7dXdc/OfdEW6unZRSl7cqp"],[5,260,260]]],[1,"687blJ+qBHaJdgr+r1KTNu",null,null,null,-1,0]],[9,"points1",1,1,[-8,-9,-10,-11,-12,-13,-14],[[5,-7,[0,"5aRno1HaNJTp1bqsVER3dm"]]],[1,"8cEnMv/dtNtYT7DzjMJDhQ",null,null,null,1,0],[1,-81.242,-68.723,0]],[10,"points2",1,1,[-16,-17,-18,-19,-20,-21,-22],[[5,-15,[0,"feBELKqGdHgoNKgCEpnCqx"]]],[1,"fbsEG6gBhM0rnzKxEYRFmm",null,null,null,1,0],[1,33.098,-62.425,0],[1,-1,1,1]],[3,"icon1",1,1,[[2,-23,[0,"cfzEeiLt9DK4gMTVpjj04s"],[5,546,500]],[6,2,false,-24,[0,"3bWnRDB5lKvYeo6i2YC/av"],0]],[1,"3cmCEwn35IKa3hkU9E8Npl",null,null,null,1,0],[1,-77.144,-3.347,0]],[11,"icon2",1,1,[[2,-25,[0,"98JlE46ehIJLvq7CzLE1U7"],[5,546,500]],[6,2,false,-26,[0,"d8CMyHlwxJ178cgLcxTe1C"],1]],[1,"08IAsUJdNO34CMA6CaNlpk",null,null,null,1,0],[1,34.344,-8.042,0],[1,-1,1,1]],[3,"pos1",1,2,[[2,-27,[0,"b4P5n6qwpIlYu5FjcQjDFU"],[5,30,30]],[4,-28,[0,"40+/WdCetP8YqYQGKCkahX"],2]],[1,"80ausahlNGGaJFMQXp8ZqX",null,null,null,1,0],[1,-54.143,127.51,0]],[3,"pos2",1,2,[[2,-29,[0,"2aICJ9MepIzKp6XhTtzkOs"],[5,30,30]],[4,-30,[0,"caFfCgRC5OKa3CqGWOG3+k"],3]],[1,"83Vjf6P25KPpeOT3vaRIB/",null,null,null,1,0],[1,-123.006,52.91,0]],[3,"pos3",1,2,[[2,-31,[0,"6a0jXxXKpPDYgr4SCJx/G1"],[5,30,30]],[4,-32,[0,"8eu7ysgo1FiYMlLoyHzvxk"],4]],[1,"2doeuJBTlFPpceuIVrKNT2",null,null,null,1,0],[1,-118.134,-15.376,0]],[3,"pos4",1,2,[[2,-33,[0,"b9E0dnyMxJPJBnlXLqK0t8"],[5,30,30]],[4,-34,[0,"fbtniAFltFq7sR45WPUpP3"],5]],[1,"39WiHZOjtGWoAYl7GxhnM/",null,null,null,1,0],[1,62.315,-124.721,0]],[3,"pos5",1,2,[[2,-35,[0,"6dcjI43ahN55iqyR4lh1Vh"],[5,30,30]],[4,-36,[0,"9cmd5r451JEqfzP+0o9YQp"],6]],[1,"a80Hq9m6dJUr7pAGpUrgMa",null,null,null,1,0],[1,118.556,-93.32,0]],[3,"pos6",1,2,[[2,-37,[0,"16f1VwfeBGuqWp+yTc1bo5"],[5,30,30]],[4,-38,[0,"30dDGsiOpJ66IMYJ9rY9Tv"],7]],[1,"069NrME+pDvYra32RZHU4Q",null,null,null,1,0],[1,125.276,16.709,0]],[3,"pos7",1,2,[[2,-39,[0,"faJwb20xpBII0c1sLwOfqR"],[5,30,30]],[4,-40,[0,"536J5w6gFPU49Dh4EN7pV5"],8]],[1,"cc3lk4+51DqKMZ3hGmjbch",null,null,null,1,0],[1,61.698,92.266,0]],[3,"pos1",1,3,[[2,-41,[0,"12GpTH56VGcLt6xcuNTjzv"],[5,30,30]],[4,-42,[0,"ecrrJaxHFHkaEI1X5Qx5W9"],9]],[1,"dd0q10pPZESYiQw88glLRd",null,null,null,1,0],[1,-54.143,127.51,0]],[3,"pos2",1,3,[[2,-43,[0,"80BygCJ3dIEqfAaIJg141S"],[5,30,30]],[4,-44,[0,"3bnwwUQHVLUYJiTOTEAkfT"],10]],[1,"69FM+4S6lP0Yw436HO+A6K",null,null,null,1,0],[1,-123.006,52.91,0]],[3,"pos3",1,3,[[2,-45,[0,"05cIx84XRB9ojAbq1hgg5u"],[5,30,30]],[4,-46,[0,"32vcT1g75DzrcydMGC/oIL"],11]],[1,"3970JF4E9EH6YRXWuYmgXa",null,null,null,1,0],[1,-118.134,-15.376,0]],[3,"pos4",1,3,[[2,-47,[0,"a9yuYs0gRAEpTZI7F9t+3b"],[5,30,30]],[4,-48,[0,"abyPhHV5pGi5dNVuHJV56u"],12]],[1,"d0R+kkIppAiazDdISHn6w9",null,null,null,1,0],[1,62.315,-124.721,0]],[3,"pos5",1,3,[[2,-49,[0,"ea2pyc9NNPKrcE705FV/H6"],[5,30,30]],[4,-50,[0,"3aKo9/PUBEsKF9BwOAawvj"],13]],[1,"57qzZf6Q1NzqJZWGuhpnpf",null,null,null,1,0],[1,118.556,-93.32,0]],[3,"pos6",1,3,[[2,-51,[0,"a5hTxlf2tNk4xtzc50jlBw"],[5,30,30]],[4,-52,[0,"0eJnccrIJAOIzD5A9RGjNT"],14]],[1,"b4vUopUodKnp1ZzOEzbV3m",null,null,null,1,0],[1,125.276,16.709,0]],[3,"pos7",1,3,[[2,-53,[0,"00w5NMXKJEdbtFZQrTaTEe"],[5,30,30]],[4,-54,[0,"8fgzI5qtxFbp91tHhdkPTa"],15]],[1,"92VMis8XZLAJpC7lv02fko",null,null,null,1,0],[1,61.698,92.266,0]]],0,[0,2,1,0,0,1,0,-1,4,0,-2,5,0,-3,2,0,-4,3,0,0,2,0,-1,6,0,-2,7,0,-3,8,0,-4,9,0,-5,10,0,-6,11,0,-7,12,0,0,3,0,-1,13,0,-2,14,0,-3,15,0,-4,16,0,-5,17,0,-6,18,0,-7,19,0,0,4,0,0,4,0,0,5,0,0,5,0,0,6,0,0,6,0,0,7,0,0,7,0,0,8,0,0,8,0,0,9,0,0,9,0,0,10,0,0,10,0,0,11,0,0,11,0,0,12,0,0,12,0,0,13,0,0,13,0,0,14,0,0,14,0,0,15,0,0,15,0,0,16,0,0,16,0,0,17,0,0,17,0,0,18,0,0,18,0,0,19,0,0,19,0,3,1,54],[0,0,0,0,0,0,0,0,0,0,0,0,0,0,0,0],[1,1,1,1,1,1,1,1,1,1,1,1,1,1,1,1],[1,1,0,0,0,0,0,0,0,0,0,0,0,0,0,0]],[[{"name":"scene_item_1001501","rect":{"x":146,"y":178,"width":254,"height":248},"offset":{"x":0,"y":-52},"originalSize":{"width":546,"height":500},"rotated":false,"capInsets":[0,0,0,0],"vertices":{"rawPosition":[-127,-124,0,127,-124,0,-127,124,0,127,124,0],"indexes":[0,1,2,2,1,3],"uv":[146,322,400,322,146,74,400,74],"nuv":[0.2673992673992674,0.148,0.7326007326007326,0.148,0.2673992673992674,0.644,0.7326007326007326,0.644],"minPos":{"x":-127,"y":-124,"z":0},"maxPos":{"x":127,"y":124,"z":0}},"packable":true,"pixelsToUnit":100,"pivot":{"x":0.5,"y":0.5},"meshType":0}],[3],0,[0],[4],[2]]]]
