[1,["7a0KSo4edDqJN5vDSYAIx5@6c48a"],["_textureSource"],["cc.SpriteFrame"],0,[{"name":"icon_2000701","rect":{"x":25,"y":56,"width":150,"height":89},"offset":{"x":0,"y":-0.5},"originalSize":{"width":200,"height":200},"rotated":false,"capInsets":[0,0,0,0],"vertices":{"rawPosition":[-75,-44.5,0,75,-44.5,0,-75,44.5,0,75,44.5,0],"indexes":[0,1,2,2,1,3],"uv":[25,144,175,144,25,55,175,55],"nuv":[0.125,0.275,0.875,0.275,0.125,0.72,0.875,0.72],"minPos":{"x":-75,"y":-44.5,"z":0},"maxPos":{"x":75,"y":44.5,"z":0}},"packable":true,"pixelsToUnit":100,"pivot":{"x":0.5,"y":0.5},"meshType":0}],[0],0,[0],[0],[0]]
